pelican/plugins/featured_image/__init__.py
pelican/plugins/featured_image/featured_image.py
pelican/plugins/featured_image/test_featured_image.py
pelican_featured_image-1.1.0.dist-info/METADATA
pelican_featured_image-1.1.0.dist-info/WHEEL
pelican_featured_image-1.1.0.dist-info/entry_points.txt
pelican_featured_image-1.1.0.dist-info/RECORD
